README.rst
setup.py
kek/__init__.py
kek/__main__.py
kek.egg-info/PKG-INFO
kek.egg-info/SOURCES.txt
kek.egg-info/dependency_links.txt
kek.egg-info/entry_points.txt
kek.egg-info/requires.txt
kek.egg-info/top_level.txt