Metadata-Version: 1.2
Name: kek
Version: 0.1.0a2
Summary: Simple tool for automating repetitive tasks
Home-page: https://github.com/martyanov/kek
Author: Andrey Martyanov
Author-email: andrey@martyanov.com
License: UNKNOWN
Keywords: development
Platform: UNKNOWN
Classifier: Development Status :: 3 - Alpha
Classifier: Intended Audience :: Developers
Classifier: Topic :: Software Development :: Build Tools
Classifier: License :: OSI Approved :: MIT License
Classifier: Programming Language :: Python :: 3
Classifier: Programming Language :: Python :: 3.4
Classifier: Programming Language :: Python :: 3.5
Classifier: Programming Language :: Python :: 3.6
Requires-Python: >=3.4
